filoani/__init__.py
filoani-0.1.1.dist-info/licenses/LICENSE
jkanime/__init__.py
jkanime/unified.py
python/__init__.py
python/api_server.py
python/jkanime_v2.py
filoani-0.1.1.dist-info/METADATA
filoani-0.1.1.dist-info/WHEEL
filoani-0.1.1.dist-info/top_level.txt
filoani-0.1.1.dist-info/RECORD
