Metadata-Version: 2.4
Name: filoani
Version: 0.1.1
Summary: API FiloAni: unificación de JkAnime y AnimeFLV (Python)
Author-email: "Chris M." <chrisperezsantiago1@gmail.com>
License: MIT
Requires-Python: >=3.9
License-File: LICENSE
Requires-Dist: requests>=2.31.0
Requires-Dist: beautifulsoup4>=4.12.0
Provides-Extra: server
Requires-Dist: fastapi>=0.111.0; extra == "server"
Requires-Dist: uvicorn>=0.23.0; extra == "server"
Provides-Extra: animeflv
Requires-Dist: animeflv>=0.1.0; extra == "animeflv"
Provides-Extra: fuzzy
Requires-Dist: rapidfuzz>=3.9.0; extra == "fuzzy"
Dynamic: license-file
